codemao/__init__.py
codemao/detect.py
codemao/image.py
codemao/mtcnn_detector.py
codemao/show.py
codemao/take_photo.py
codemao/ui.py
codemao/utils.py
codemao/data/fer2013_mini_XCEPTION.102-0.66.hdf5
codemao/data/simple_CNN.81-0.96.hdf5
codemao/data/age/model-0000.params
codemao/data/age/model-symbol.json
codemao/data/mtcnn-model/det1-0001.params
codemao/data/mtcnn-model/det1-symbol.json
codemao/data/mtcnn-model/det1.caffemodel
codemao/data/mtcnn-model/det1.prototxt
codemao/data/mtcnn-model/det2-0001.params
codemao/data/mtcnn-model/det2-symbol.json
codemao/data/mtcnn-model/det2.caffemodel
codemao/data/mtcnn-model/det2.prototxt
codemao/data/mtcnn-model/det3-0001.params
codemao/data/mtcnn-model/det3-symbol.json
codemao/data/mtcnn-model/det3.caffemodel
codemao/data/mtcnn-model/det3.prototxt
codemao/data/mtcnn-model/det4-0001.params
codemao/data/mtcnn-model/det4-symbol.json
codemao/data/mtcnn-model/det4.caffemodel
codemao/data/mtcnn-model/det4.prototxt
Codemao-0.0.17.dist-info/METADATA
Codemao-0.0.17.dist-info/WHEEL
Codemao-0.0.17.dist-info/top_level.txt
Codemao-0.0.17.dist-info/RECORD
